lighter_torch
